fbmodules/__init__.py
fbmodules/src/__init__.py
fbmodules/src/fbmodules.py
fbmodules/src/steam.py
fbmodules/src/web.py
fbmodules-0.0.3.dist-info/LICENSE.MD
fbmodules-0.0.3.dist-info/METADATA
fbmodules-0.0.3.dist-info/WHEEL
fbmodules-0.0.3.dist-info/top_level.txt
fbmodules-0.0.3.dist-info/RECORD
