Metadata-Version: 2.1
Name: fbmodules
Version: 0.0.3
Summary: Just a simple set of modules 
Home-page: https://github.com/timotofcourse/fb-modules
Author: Timot
Author-email: filmabemtv2@gmail.com
License: 
Classifier: License :: OSI Approved :: MIT License
Classifier: Programming Language :: Python :: 3.10
Classifier: Operating System :: OS Independent
Requires-Python: >=3.10
License-File: LICENSE.MD
Requires-Dist: ruamel.yaml >=0.18.6
Requires-Dist: winotify >=1.1.0
Provides-Extra: dev
Requires-Dist: twine >=5.0.0 ; extra == 'dev'
Requires-Dist: uvicorn >=0.2.2 ; extra == 'dev'
Requires-Dist: gradio ==3.44.1 ; extra == 'dev'
